phantasma_py/__init__.py
phantasma_py/API/__init__.py
phantasma_py/API/api_client.py
phantasma_py/API/configuration.py
phantasma_py/API/rest.py
phantasma_py/API/API/__init__.py
phantasma_py/API/API/account_api.py
phantasma_py/API/API/auction_api.py
phantasma_py/API/API/block_api.py
phantasma_py/API/API/chain_api.py
phantasma_py/API/API/connection_api.py
phantasma_py/API/API/contract_api.py
phantasma_py/API/API/leaderboard_api.py
phantasma_py/API/API/nexus_api.py
phantasma_py/API/API/organization_api.py
phantasma_py/API/API/platform_api.py
phantasma_py/API/API/rpc_api.py
phantasma_py/API/API/sale_api.py
phantasma_py/API/API/storage_api.py
phantasma_py/API/API/token_api.py
phantasma_py/API/API/transaction_api.py
phantasma_py/API/API/validator_api.py
phantasma_py/API/models/__init__.py
phantasma_py/API/models/abi_event_result.py
phantasma_py/API/models/abi_method_result.py
phantasma_py/API/models/abi_parameter_result.py
phantasma_py/API/models/account_result.py
phantasma_py/API/models/address.py
phantasma_py/API/models/address_kind.py
phantasma_py/API/models/archive_result.py
phantasma_py/API/models/auction_result.py
phantasma_py/API/models/balance_result.py
phantasma_py/API/models/block_result.py
phantasma_py/API/models/chain_result.py
phantasma_py/API/models/contract_result.py
phantasma_py/API/models/crowdsale_result.py
phantasma_py/API/models/event_result.py
phantasma_py/API/models/governance_result.py
phantasma_py/API/models/interop_result.py
phantasma_py/API/models/leaderboard_result.py
phantasma_py/API/models/leaderboard_row_result.py
phantasma_py/API/models/net_info_peer.py
phantasma_py/API/models/net_info_peer_connection_status.py
phantasma_py/API/models/net_info_peer_connection_status_channel.py
phantasma_py/API/models/net_info_peer_connection_status_monitor.py
phantasma_py/API/models/nexus_result.py
phantasma_py/API/models/node_info.py
phantasma_py/API/models/node_info_other.py
phantasma_py/API/models/node_info_protocol_version.py
phantasma_sdk_py-1.0.11.dist-info/licenses/LICENSE
phantasma_sdk_py-1.0.11.dist-info/METADATA
phantasma_sdk_py-1.0.11.dist-info/WHEEL
phantasma_sdk_py-1.0.11.dist-info/top_level.txt
phantasma_sdk_py-1.0.11.dist-info/RECORD
