Metadata-Version: 2.4
Name: phantasma-sdk-py
Version: 1.0.11
Summary: Phantasma SDK for Python
Home-page: https://phantasma.info/
Author-email: info@phantasma.info
Project-URL: Homepage, https://github.com/phantasma-io/Phantasma-Py
Requires-Python: >=3.6
License-File: LICENSE
Requires-Dist: certifi>=14.05.14
Requires-Dist: six>=1.10
Requires-Dist: python_dateutil>=2.5.3
Requires-Dist: setuptools>=21.0.0
Requires-Dist: urllib3>=1.15.1
Requires-Dist: requests>=2.18.4
Requires-Dist: base58>=2.1.1
Requires-Dist: cryptography>=41.0.7
Requires-Dist: numpy>=1.26.2
Requires-Dist: ecpy>=1.2.5
Dynamic: author-email
Dynamic: home-page
Dynamic: license-file
Dynamic: requires-python
